aceti/__init__.py
aceti/common_maps/__init__.py
aceti/common_maps/map_creator.py
aceti/common_maps/map_importer.py
aceti/gui/GUI.py
aceti/gui/__init__.py
aceti/gui/assets.py
aceti/gui/create grid.py
aceti/gui/create_tiles_db.py
aceti/gui/serverside.py
aceti/gui/shared.py
aceti/gui/assets/empty.csv
aceti/gui/assets/icon_aceti.png
aceti/gui/assets/icon_gaussian.png
aceti/gui/assets/icon_path_planning.png
aceti/gui/assets/icon_ship.png
aceti/gui/assets/icon_trash_log.png
aceti/gui/assets/icon_water_trash.png
aceti/gui/assets/logo-ace-ti.png
aceti/gui/assets/lupa.png
aceti/gui/assets/mapgeneration.png
aceti/gui/assets/off.png
aceti/gui/assets/on.png
aceti/gui/assets/pause.png
aceti/gui/assets/play.png
aceti/gui/assets/waste - copia.png
aceti/gui/assets/waste0.png
aceti/gui/assets/waste1.png
aceti/gui/assets/Maps/Alamillo30x49latlon.npy
aceti/gui/assets/Maps/Alamillo30x49mask.npy
aceti/gui/assets/Maps/Alamillo95x216grid.csv
aceti/gui/assets/Maps/Alamillo95x216plantilla.csv
aceti/gui/assets/Maps/AlamilloAccess11x15latlon.npy
aceti/gui/assets/Maps/AlamilloAccess11x15mask.npy
aceti/gui/assets/Maps/AlamilloImage2.csv
aceti/gui/assets/Maps/AlamilloImage2.png
aceti/gui/assets/Maps/AlamilloImage2.xcf
aceti/gui/assets/Maps/AlamilloSat.png
aceti/gui/assets/Maps/alamillo.csv
aceti/gui/assets/Maps/alamillo.npy
aceti/gui/assets/Maps/alamillo.png
aceti/gui/assets/Maps/alamillo.xcf
aceti/gui/assets/Maps/alamillo_big.npy
aceti/gui/assets/measures/0.png
aceti/gui/assets/measures/1.png
aceti/gui/assets/measures/10.png
aceti/gui/assets/measures/2.png
aceti/gui/assets/measures/3.png
aceti/gui/assets/measures/4.png
aceti/gui/assets/measures/5.png
aceti/gui/assets/measures/6.png
aceti/gui/assets/measures/7.png
aceti/gui/assets/measures/8.png
aceti/gui/assets/measures/9.png
aceti/gui/assets/tiles/offline_tiles.db
aceti/gui/submodules/GPModels.py
aceti/gui/submodules/MQTT.py
aceti/gui/submodules/database.py
aceti/gui/submodules/dijkstra.py
aceti/gui/submodules/deprecated/colorbar.py
aceti-1.0.2.dist-info/licenses/LICENSE
aceti-1.0.2.dist-info/METADATA
aceti-1.0.2.dist-info/WHEEL
aceti-1.0.2.dist-info/entry_points.txt
aceti-1.0.2.dist-info/top_level.txt
aceti-1.0.2.dist-info/RECORD
