Metadata-Version: 2.4
Name: aceti
Version: 1.0.2
Summary: A simple package to store and create maps for an experiment
Author-email: Alejandro Casado <acasado4@us.es>
License-Expression: MIT
Project-URL: Homepage, https://github.com/aceti-pub/common_maps
Project-URL: Issues, https://github.com/aceti-pub/common_maps/issues
Classifier: Development Status :: 3 - Alpha
Classifier: Intended Audience :: Education
Classifier: Programming Language :: Python :: 3
Classifier: Operating System :: MacOS :: MacOS X
Classifier: Operating System :: Microsoft :: Windows
License-File: LICENSE
Requires-Dist: numpy
Requires-Dist: matplotlib
Requires-Dist: pillow
Requires-Dist: tqdm
Requires-Dist: pyproj
Requires-Dist: customtkinter
Requires-Dist: screeninfo
Requires-Dist: tkcalendar
Dynamic: license-file
